docraptor/__init__.py
docraptor/api_client.py
docraptor/configuration.py
docraptor/exceptions.py
docraptor/model_utils.py
docraptor/rest.py
docraptor/schemas.py
docraptor/api/__init__.py
docraptor/api/doc_api.py
docraptor/api/doc_api_endpoints/__init__.py
docraptor/api/doc_api_endpoints/create_async_doc.py
docraptor/api/doc_api_endpoints/create_doc.py
docraptor/api/doc_api_endpoints/create_hosted_async_doc.py
docraptor/api/doc_api_endpoints/create_hosted_doc.py
docraptor/api/doc_api_endpoints/expire.py
docraptor/api/doc_api_endpoints/get_async_doc.py
docraptor/api/doc_api_endpoints/get_async_doc_status.py
docraptor/apis/__init__.py
docraptor/model/__init__.py
docraptor/model/async_doc.py
docraptor/model/doc.py
docraptor/model/doc_status.py
docraptor/model/prince_options.py
docraptor/models/__init__.py
docraptor/models/async_doc.py
docraptor/models/doc.py
docraptor/models/doc_status.py
docraptor/models/prince_options.py
test/__init__.py
test/async.py
test/file.py
test/hosted_async.py
test/hosted_expire.py
test/hosted_sync.py
test/invalid_async.py
test/invalid_sync.py
test/sync.py
test/xlsx.py
docraptor-3.1.0.dist-info/LICENSE
docraptor-3.1.0.dist-info/METADATA
docraptor-3.1.0.dist-info/WHEEL
docraptor-3.1.0.dist-info/top_level.txt
docraptor-3.1.0.dist-info/RECORD
