Metadata-Version: 2.1
Name: docraptor
Version: 3.1.0
Summary: DocRaptor
Home-page: 
Author: OpenAPI Generator community
Author-email: team@openapitools.org
License: MIT
Keywords: OpenAPI,OpenAPI-Generator,DocRaptor
License-File: LICENSE
Requires-Dist: urllib3>=1.25.3
Requires-Dist: six>=1.10
Requires-Dist: python-dateutil
